{
  "description": "Venom (#VNM) is a hyper-deflationary token with unique rewards, true burn mechanics, and a strong community-driven ecosystem.",
  "links": [
    {
      "name": "Telegram",
      "url": "https://t.me/VenomVNM",
      "type": "link"
    },
    {
      "name": "Twitter",
      "url": "https://twitter.com/VenomCryptoVNM",
      "type": "link"
    },
    {
      "name": "YouTube",
      "url": "https://www.youtube.com/@VenomCrypto",
      "type": "link"
    }
  ],
  "icon": "icon.png"
}